{
  "haftaici": [
    {
      "label": "HAFTA İÇİ SEFER SAATLERİ",
      "url": "https://ulasim.canakkale.bel.tr/wp-content/uploads/2018/02/7-MAYIS-1.pdf"
    },
    {
      "label": "12 MAYIS İTİBARİYLE HAFTA İÇİ SEFER SAATLERİ",
      "url": "https://ulasim.canakkale.bel.tr/wp-content/uploads/2018/02/12-MAYIS-1.pdf"
    }
  ],
  "haftasonu": [
    {
      "label": "HAFTA SONU SEFER SAATLERİ",
      "url": "https://ulasim.canakkale.bel.tr/wp-content/uploads/2018/02/9-MAYIS-5.pdf"
    }
  ],
  "arefe": [],
  "bayram": [],
  "diger": []
}
